README.md
setup.py
autoalchemy/__init__.py
autoalchemy/build_database.py
autoalchemy/cli.py
autoalchemy/dataframe_parser.py
autoalchemy/schema_code_generator.py
autoalchemy/utils.py
autoalchemy.egg-info/PKG-INFO
autoalchemy.egg-info/SOURCES.txt
autoalchemy.egg-info/dependency_links.txt
autoalchemy.egg-info/entry_points.txt
autoalchemy.egg-info/not-zip-safe
autoalchemy.egg-info/requires.txt
autoalchemy.egg-info/top_level.txt