Metadata-Version: 1.2
Name: autoalchemy
Version: 0.0.1
Summary: Push raw data files to a SQL database by automatically generating a schema, with sane typing and naming.
Home-page: https://github.com/ericchang00/autoalchemy
Author: Eric Chang
Author-email: ericchang00@gmail.com
License: MIT license
Keywords: autoalchemy
Platform: UNKNOWN
Classifier: Development Status :: 2 - Pre-Alpha
Classifier: Intended Audience :: Developers
Classifier: License :: OSI Approved :: MIT License
Classifier: Natural Language :: English
Classifier: Programming Language :: Python :: 3.5
Classifier: Programming Language :: Python :: 3.6
Requires-Python: >=3.5
